pcki/__init__.py
basic_math_ops-1.2.dist-info/METADATA
basic_math_ops-1.2.dist-info/WHEEL
basic_math_ops-1.2.dist-info/license.txt
basic_math_ops-1.2.dist-info/top_level.txt
basic_math_ops-1.2.dist-info/RECORD
